file_type_guesser/__init__.py
file_type_guesser/constants.py
file_type_guesser/core.py
file_type_guesser/signatures.py
file_type_guesser/types.py
file_type_guesser-0.2.0.dist-info/LICENSE
file_type_guesser-0.2.0.dist-info/METADATA
file_type_guesser-0.2.0.dist-info/WHEEL
file_type_guesser-0.2.0.dist-info/top_level.txt
file_type_guesser-0.2.0.dist-info/RECORD
