Metadata-Version: 2.1
Name: file-type-guesser
Version: 0.2.0
Summary: Guess a files type from its content and extension
Home-page: https://github.com/enchant97/python-file-type-guesser
Author: Leo Spratt
Author-email: "contact@enchantedcode.co.uk"
License: MIT
Project-URL: Change Log, https://github.com/enchant97/python-file-type-guesser/blob/main/CHANGELOG.md
Project-URL: Documentation, https://python-file-type-guesser.readthedocs.io/en/stable/
Keywords: git scm
Platform: UNKNOWN
Classifier: License :: OSI Approved :: MIT License
Classifier: Development Status :: 5 - Production/Stable
Classifier: Operating System :: OS Independent
Classifier: Programming Language :: Python :: 3
Classifier: Programming Language :: Python :: 3.10
Classifier: Intended Audience :: Developers
Classifier: Topic :: Text Processing
Classifier: Topic :: Software Development :: Libraries :: Python Modules
Classifier: Topic :: Utilities
Requires-Python: >=3.10
License-File: LICENSE
